Workbook

Sheet Guía
A1: Dirección de Registro Civil y Documentación — Emisión de Partida de Nacimiento
A2: Caso ficticio de un ente público que quiere digitalizar la emisión de documentos, con la misma metodología usada para Clínica Bermejo, Café Aurora y Hotel Costa Azul
A4: Cómo usar este archivo
A5: Pestaña | B5: Contenido | C5: Qué hacer
A6: Contexto de la Organización | B6: Ficha del organismo ficticio: qué es, qué servicios presta, cómo es hoy el proceso de emisión de documentos, y cuál es el objetivo del proyecto de digitalización. | C6: Leer primero: da el marco institucional y el 'por qué' del proyecto que enmarca al resto de las pestañas.
A7: Buyer Persona | B7: Ficha de Silvina Duarte, persona ficticia que representa al ciudadano que necesita el trámite de forma puntual y urgente: datos generales, objetivos, frustraciones (ligadas a los hallazgos), motivaciones y factores de satisfacción. | C7: Usar como referencia rápida de 'para quién' se diseña el resto del archivo (reseñas, CJM, blueprint).
A8: Reseñas y Encuesta | B8: Reseñas ficticias de Google Maps sobre la sede del organismo, construidas para ilustrar 5 hallazgos típicos de un trámite público no digitalizado, y agregados de la encuesta (NPS, CSAT, CES) calculados desde 'Respuestas Encuesta'. | C8: Las reseñas ya están cargadas. Los agregados de encuesta se recalculan solos cuando actualices la base de respuestas.
A9: Respuestas Encuesta | B9: Base de 50 respuestas individuales de una encuesta de satisfacción ciudadana (dato de prueba/ficticio): NPS, CSAT, CES, aspecto valorado, categoría asociada y comentario. | C9: Reemplazar estas 50 filas por datos reales cuando existan; el resto del archivo se recalcula automáticamente.
A10: Indicadores | B10: Métricas calculadas automáticamente a partir de las reseñas y de las 50 respuestas de encuesta: rating promedio, % positivas/negativas, menciones por categoría, NPS y CSAT, cada uno con su definición e interpretación del resultado obtenido. | C10: No requiere carga manual: todo se recalcula solo desde 'Reseñas y Encuesta' y 'Respuestas Encuesta'.
A11: Customer Journey Map | B11: Mapa As Is de las 5 etapas / 10 subetapas del recorrido del ciudadano: descripción de cada etapa, touchpoints, acciones, emociones, dolores y oportunidades por subetapa. | C11: Base para trabajar en clase o ajustar con el grupo. Cada columna cita la evidencia de la que sale (reseña / hallazgo).
A12: Customer Journey Map (To Be) | B12: Misma estructura que el As Is, pero con el recorrido deseado una vez digitalizado el trámite: touchpoints mejorados, emociones esperadas, la mejora que resuelve cada dolor y el KPI para medirla. | C12: Usar para diseñar el plan de digitalización; cada subetapa está vinculada al hallazgo del As Is que resuelve.
A13: Service Blueprint | B13: Complementa el CJM As Is con la vista interna del servicio: evidencia física, acciones del ciudadano, frontstage, backstage, procesos de soporte y punto de fallo potencial por subetapa. | C13: Usar para identificar qué proceso o sistema interno hay que ajustar para resolver cada punto de dolor del CJM.
A14: Insights y Oportunidades | B14: Síntesis de los 5 hallazgos con nivel de impacto y prioridad sugerida. | C14: Usar como tablero de priorización; el campo Prioridad tiene lista desplegable.
A16: Convención de colores
B17: Celda para completar (input del usuario / dato de la encuesta)
B18: Indicador o comentario en rango positivo
B19: Indicador o comentario en rango negativo / de atención
A21: Caso: es un caso 100% ficticio (la Dirección de Registro Civil y Documentación de la Provincia de Nueva Trinidad no existe), construido replicando la misma metodología aplicada a los casos de Clínica Bermejo, Café Aurora y Hotel Costa Azul, ahora aplicada a un organismo público que busca digitalizar un trámite.

Sheet Contexto de la Organización
A1: Contexto de la Organización (ficticia)
A2: Dirección de Registro Civil y Documentación de la Provincia de Nueva Trinidad (DRCyD)
A6: Datos generales del organismo
A7: Nombre (ficticio) | B7: Dirección de Registro Civil y Documentación de la Provincia de Nueva Trinidad (DRCyD)
A8: Tipo de organismo | B8: Organismo público provincial, dependiente del Ministerio de Gobierno
A9: Jurisdicción | B9: Provincia de Nueva Trinidad (ficticia): ~850.000 habitantes, 1 sede central y 12 delegaciones municipales
A10: Misión | B10: Registrar los hechos y actos del estado civil de las personas (nacimientos, matrimonios, defunciones) y emitir la documentación asociada con validez legal en toda la provincia
A11: Marco legal | B11: Ley provincial de Registro Civil y Capacidad de las Personas (ficticia); el proyecto de digitalización busca adherir a la normativa de firma digital vigente
A13: Servicios que presta
A14: • Emisión de partidas de nacimiento, matrimonio y defunción.
A15: • Inscripción de nacimientos y matrimonios.
A16: • Rectificaciones y actualizaciones de datos registrales.
A17: • Certificados de supervivencia y otros trámites conexos.
A19: Trámite foco de este análisis: Emisión de Partida de Nacimiento — es el trámite más solicitado (~60% del volumen total) y el elegido para el proyecto piloto de digitalización.
A21: Volumen y estado actual del proceso
A22: Volumen anual | B22: ≈ 180.000 partidas emitidas por año en toda la provincia; ~65% se solicitan en la sede central
A23: Canal actual | B23: 100% presencial: el ciudadano debe sacar turno (telefónico o presencial) y presentarse en la sede o delegación
A24: Tiempo de espera de turno | B24: Entre 20 y 45 días en temporada alta (marzo, inicio de clases)
A25: Tiempo de emisión | B25: Entre 5 y 10 días hábiles una vez presentado el trámite
A26: Seguimiento del trámite | B26: No existe opción de seguimiento online del estado del trámite
A27: Información de requisitos | B27: Publicada en la web institucional, pero desactualizada en varias delegaciones del interior
A29: Objetivo del proyecto de digitalización
A30: • Permitir la solicitud y el seguimiento del trámite 100% online.
A31: • Implementar la partida de nacimiento digital, con firma electrónica y validación por código QR.
A32: • Reducir el tiempo total del trámite de ~30 días a menos de 5 días hábiles.
A33: • Reducir la necesidad de presencialidad, especialmente para ciudadanos del interior de la provincia.
A35: Stakeholders internos
A36: • Dirección de Registro Civil (sponsor del proyecto).
A37: • Área de Sistemas / Tecnología (desarrollo de la plataforma digital).
A38: • Mesa de entradas y personal de atención al público (usuarios internos del nuevo sistema).
A39: • Delegaciones municipales del interior (12 sedes descentralizadas).
A40: • Área legal (validación normativa de la firma digital y de la validez del documento).
A42: Restricciones / condicionantes
... A52: • Nivel de satisfacción ciudadana (NPS / CSAT) del trámite.

Sheet Buyer Persona
A1: Buyer Persona — Silvina Duarte (perfil ficticio)
A2: Representa al ciudadano que necesita el trámite de forma puntual y urgente (DRCyD)
A4: Nota: es un personaje ficticio construido para un caso también ficticio (DRCyD). No representa a una ciudadana real.
A6: Datos generales
A7: Nombre (ficticio) | B7: Silvina Duarte
A8: Edad | B8: 45 años
A9: Ubicación | B9: Puerto Alegre, a 120 km de la sede central del Registro Civil
A10: Ocupación | B10: Empleada administrativa en un comercio local
A11: Estado civil | B11: Casada, un hijo de 6 años
A12: Segmento | B12: Ciudadanos que necesitan un trámite puntual y urgente, sin relación recurrente con el organismo
A13: Motivo del trámite | B13: Necesita la partida de nacimiento de su hijo para inscribirlo en la escuela primaria antes de marzo
A14: Frecuencia de uso del organismo | B14: Muy baja: una vez cada varios años, cuando surge una necesidad puntual
A16: "No tengo tiempo de perder un día entero de trabajo para hacer un trámite que debería resolverse en minutos."
A18: Bio / Contexto
A19: Silvina vive en Puerto Alegre, una localidad del interior de la provincia, lejos de la sede central del Registro Civil. No tiene mucha experiencia con trámites online y depende de lo que encuentra en la web oficial (a veces desactualizada) o de lo que le cuentan otros vecinos que ya hicieron el mismo trámite. Para resolverlo tiene que pedir el día en el trabajo y viajar hasta la sede, algo que le genera bastante estrés porque tiene una fecha límite externa (la inscripción escolar de su hijo) que no depende de ella.
A21: Objetivos
A22: • Conseguir la partida de nacimiento de su hijo a tiempo para la inscripción escolar.
A23: • Resolver el trámite sin perder un día completo de trabajo ni viajar 120 km.
A24: • Entender con claridad qué requisitos necesita antes de ir.
A26: Frustraciones (ligadas a los hallazgos)
A27: Frustración | B27: Hallazgo relacionado
A28: Los turnos disponibles estaban muy lejos en el tiempo; no llegaba a la fecha límite de la escuela. | B28: Hallazgo 2
A29: La información de requisitos en la web no estaba actualizada. | B29: Hallazgo 4
A30: No existe una forma de hacer el trámite a distancia: tiene que viajar sí o sí. | B30: Hallazgo 5
A31: Le preocupa que haya un error en los datos del documento y tener que reiniciar todo el trámite. | B31: Hallazgo 3
A33: Motivaciones
A34: • Evitar perder días de trabajo por un trámite administrativo.
A35: • Poder resolver trámites del Estado con la misma facilidad que otras gestiones online (banco, servicios).
A36: • Que la información oficial sea clara y confiable.
A38: Canales que usa
A39: Web oficial del organismo, teléfono de la sede, boca a boca de otros vecinos y Google Maps para consultar horarios y reseñas antes de ir.
A41: Factores que más valora del proceso (de mayor a menor peso)
A42: 1. Rapidez del trámite (que no le insuma más tiempo del necesario).
A43: 2. Claridad de la información sobre requisitos.
A44: 3. Posibilidad de resolverlo a distancia, sin viajar.
A45: 4. Trato del personal cuando finalmente es atendida.
A47: Relación con el organismo
A48: A diferencia de los casos de la cafetería o el hotel, acá Silvina no elige ni puede cambiar de organismo: el vínculo es obligatorio, no comercial. Por eso la lógica de 'fidelización' no aplica igual; lo que está en juego es la confianza institucional y la carga (tiempo, viajes, incertidumbre) que el trámite le genera. Reducir esa carga es, en sí mismo, el objetivo del proyecto de digitalización.

Sheet Reseñas y Encuesta
A1: Voz del Ciudadano — Reseñas (Google Maps) y Encuesta de Satisfacción
A2: Trámite analizado: Emisión de Partida de Nacimiento (caso ficticio, DRCyD)
A4: # | B4: Fuente | C4: Autor | D4: Calificación (1-5) | E4: Antigüedad | F4: Comentario (resumen) | G4: Categoría / Hallazgo | H4: Sentimiento
A5: 1 | B5: Google Maps | C5: Miriam Casas | D5: 5 | E5: Hace 6 meses | F5: La empleada que me atendió fue muy amable y me explicó todo el trámite paso a paso. | G5: 1) Buen trato del personal cuando atiende | H5: Positivo
A6: 2 | B6: Google Maps | C6: Ramiro Estévez | D6: 5 | E6: Hace 10 meses | F6: A pesar de la fila, una vez que te atienden el trato es excelente. | G6: 1) Buen trato del personal cuando atiende | H6: Positivo
A7: 3 | B7: Google Maps | C7: Débora Sosa | D7: 4 | E7: Hace 1 año | F7: El personal de mesa de entradas siempre dispuesto a ayudar, aunque el sistema es lento. | G7: 1) Buen trato del personal cuando atiende | H7: Mixto
A8: 4 | B8: Google Maps | C8: Reseña sin nombre (cita textual) | E8: N/D | F8: "Se nota que quieren ayudar, el problema es el sistema, no la gente." | G8: 1) Buen trato del personal cuando atiende | H8: Positivo
A9: 5 | B9: Google Maps | C9: Walter Guzmán | D9: 2 | E9: Hace 3 meses | F9: Pedí turno y me dieron para dentro de 45 días. Necesitaba la partida antes. | G9: 2) Turnos escasos y demoras | H9: Negativo
A10: 6 | B10: Google Maps | C10: Norma Villalba | D10: 1 | E10: Hace 4 meses | F10: Fui sin turno porque no conseguía online y me dijeron que tenía que sacar turno igual. Perdí el día. | G10: 2) Turnos escasos y demoras | H10: Negativo
A11: 7 | B11: Google Maps | C11: Ariel Coronel | D11: 1 | E11: Hace 2 meses | F11: Me dieron la partida con un error en la fecha de nacimiento. Tuve que volver a hacer todo el trámite de nuevo. | G11: 3) Errores en los datos del documento emitido | H11: Negativo
A12: 8 | B12: Google Maps | C12: Yesica Molina | D12: 2 | E12: Hace 5 meses | F12: El documento llegó con un dato mal tipeado, tuve que reclamar y tardaron semanas en corregirlo. | G12: 3) Errores en los datos del documento emitido | H12: Negativo
A13: 9 | B13: Google Maps | C13: Fabián Chávez | D13: 2 | E13: Hace 1 mes | F13: La página web tiene información vieja, los requisitos que pedían no eran los que decía la web. | G13: 4) Información de requisitos poco clara o desactualizada | H13: Negativo
A14: 10 | B14: Instagram | C14: Varios usuarios (consultas espontáneas) | E14: N/D | F14: Varios comentarios preguntando por requisitos del trámite, sin respuesta visible. | G14: 4) Información de requisitos poco clara o desactualizada | H14: Negativo
A15: 11 | B15: Google Maps | C15: Patricia Ledesma | D15: 1 | E15: Hace 7 meses | F15: No existe forma de hacer el trámite online, hay que ir sí o sí presencialmente aunque vivas lejos. | G15: 5) Falta de un canal 100% digital | H15: Negativo
A16: 12 | B16: Google Maps | C16: Osvaldo Ibarra | D16: 2 | E16: Hace 3 meses | F16: Vine desde 3 horas en auto porque no hay forma de gestionar esto a distancia. | G16: 5) Falta de un canal 100% digital | H16: Negativo
A17: 13 | B17: Google Maps | C17: Carla Benítez | D17: 5 | E17: Hace 9 meses | F17: Cuando por fin te atienden, la gente labura bien; lo que falla es que todo depende de ir en persona. | G17: 5) Falta de un canal 100% digital | H17: Mixto
A19: Nota: reseñas 100% ficticias, redactadas para ilustrar 5 hallazgos típicos de un trámite público no digitalizado (Fuente simulada: Google Maps e Instagram). Las calificaciones en estrellas de Instagram no aplican (N/D).
A22: Encuesta de satisfacción ciudadana
A23: Los valores de abajo se calculan automáticamente a partir de las 50 respuestas cargadas en la pestaña 'Respuestas Encuesta' (dato de prueba/ficticio).
A25: # | B25: Pregunta de la encuesta | C25: Tipo de respuesta | D25: Respuesta / Valor | E25: Escala
A26: 1 | B26: ¿Con qué probabilidad recomendarías este trámite a un familiar o amigo? | C26: Numérica (NPS) | D26: =AVERAGE('Respuestas Encuesta'!D6:D55) -> 6.16 | E26: 0 a 10
A27: 2 | B27: ¿Cómo calificarías tu satisfacción general con el trámite? | C27: Numérica (CSAT) | D27: =AVERAGE('Respuestas Encuesta'!F6:F55) -> 3.3 | E27: 1 a 5
A28: 3 | B28: ¿Qué tan rápido se resolvió el trámite? | C28: Numérica (CES simplificado) | D28: =AVERAGE('Respuestas Encuesta'!G6:G55) -> 2.98 | E28: 1 a 5
A29: 4 | B29: ¿Qué aspecto valorás más del proceso? | C29: Abierta / opción múltiple | D29: Ver detalle por respuesta en la pestaña 'Respuestas Encuesta', columna H | E29: Texto
A30: 5 | B30: ¿Qué mejorarías del trámite? | C30: Abierta | D30: Ver comentario y categoría asociada en la pestaña 'Respuestas Encuesta', columnas I-J | E30: Texto
A31: ⚠ Los promedios de arriba dependen de los datos de prueba (ficticios) cargados en 'Respuestas Encuesta'. Al reemplazar esa base por datos reales, estos valores se actualizan solos.

Sheet Respuestas Encuesta
A1: Respuestas Individuales — Encuesta de Satisfacción Ciudadana
A2: Base de 50 respuestas simuladas para practicar el cálculo de NPS, CSAT y CES (caso ficticio, DRCyD)
A3: ⚠ Estas 50 respuestas son datos de prueba (ficticios), generados para completar el ejercicio. Reemplazar por datos reales cuando existan; el resto del archivo (pestañas 'Reseñas y Encuesta' e 'Indicadores') se recalcula solo.
A5: ID | B5: Fecha | C5: Canal | D5: NPS (0-10) | E5: Clasificación NPS | F5: CSAT (1-5) | G5: CES (1-5) | H5: Aspecto más valorado | I5: Categoría asociada (hallazgo) | J5: Comentario (resumen)
A6: R001 | B6: 46096 | C6: Google Maps | D6: 7 | E6: =IF(D6>=9,"Promotor",IF(D6>=7,"Pasivo","Detractor")) -> Pasivo | F6: 4 | G6: 2 | H6: Posibilidad de hacerlo online | I6: 1) Buen trato del personal cuando atiende | J6: El empleado que me atendió fue muy amable.
A7: R002 | B7: 46101 | C7: WhatsApp | D7: 0 | E7: =IF(D7>=9,"Promotor",IF(D7>=7,"Pasivo","Detractor")) -> Detractor | F7: 4 | G7: 2 | H7: Posibilidad de hacerlo online | I7: 2) Turnos escasos y demoras | J7: Muy pocos turnos disponibles.
A8: R003 | B8: 46100 | C8: Formulario en la sede | D8: 9 | E8: =IF(D8>=9,"Promotor",IF(D8>=7,"Pasivo","Detractor")) -> Promotor | F8: 5 | G8: 3 | H8: Otro | I8: 1) Buen trato del personal cuando atiende | J8: El empleado que me atendió fue muy amable.
A9: R004 | B9: 46108 | C9: Formulario en la sede | D9: 9 | E9: =IF(D9>=9,"Promotor",IF(D9>=7,"Pasivo","Detractor")) -> Promotor | F9: 4 | G9: 5 | H9: Posibilidad de hacerlo online | I9: 1) Buen trato del personal cuando atiende | J9: Se nota que quieren ayudar.
A10: R005 | B10: 46059 | C10: WhatsApp | D10: 3 | E10: =IF(D10>=9,"Promotor",IF(D10>=7,"Pasivo","Detractor")) -> Detractor | F10: 2 | G10: 3 | H10: Posibilidad de hacerlo online | I10: 3) Errores en los datos del documento emitido | J10: Tuve que reclamar por un error en la partida.
A11: R006 | B11: 46102 | C11: Google Maps | D11: 7 | E11: =IF(D11>=9,"Promotor",IF(D11>=7,"Pasivo","Detractor")) -> Pasivo | F11: 4 | G11: 4 | H11: Posibilidad de hacerlo online | I11: 5) Falta de un canal 100% digital | J11: Tuve que viajar sí o sí para hacer el trámite.
A12: R007 | B12: 46069 | C12: Formulario en la sede | D12: 4 | E12: =IF(D12>=9,"Promotor",IF(D12>=7,"Pasivo","Detractor")) -> Detractor | F12: 3 | G12: 1 | H12: Posibilidad de hacerlo online | I12: 1) Buen trato del personal cuando atiende | J12: Se nota que quieren ayudar.
A13: R008 | B13: 46101 | C13: Encuesta telefónica | D13: 9 | E13: =IF(D13>=9,"Promotor",IF(D13>=7,"Pasivo","Detractor")) -> Promotor | F13: 5 | G13: 3 | H13: Posibilidad de hacerlo online | I13: 1) Buen trato del personal cuando atiende | J13: Se nota que quieren ayudar.
A14: R009 | B14: 46099 | C14: Encuesta telefónica | D14: 8 | E14: =IF(D14>=9,"Promotor",IF(D14>=7,"Pasivo","Detractor")) -> Pasivo | F14: 3 | G14: 2 | H14: Rapidez del trámite | I14: Sin comentario asociado | J14: -
A15: R010 | B15: 46096 | C15: WhatsApp | D15: 7 | E15: =IF(D15>=9,"Promotor",IF(D15>=7,"Pasivo","Detractor")) -> Pasivo | F15: 3 | G15: 2 | H15: Trato del personal | I15: 5) Falta de un canal 100% digital | J15: Sería mejor si se pudiera gestionar a distancia.
A16: R011 | B16: 46107 | C16: Formulario en la sede | D16: 2 | E16: =IF(D16>=9,"Promotor",IF(D16>=7,"Pasivo","Detractor")) -> Detractor | F16: 3 | G16: 2 | H16: Precisión de los datos del documento | I16: 2) Turnos escasos y demoras | J16: El turno tardó mucho en salir.
A17: R012 | B17: 46084 | C17: Google Maps | D17: 2 | E17: =IF(D17>=9,"Promotor",IF(D17>=7,"Pasivo","Detractor")) -> Detractor | F17: 2 | G17: 1 | H17: Trato del personal | I17: 3) Errores en los datos del documento emitido | J17: Encontré un error de tipeo en mis datos.
... A55: R050 | B55: 46096 | C55: Encuesta telefónica | D55: 8 | E55: =IF(D55>=9,"Promotor",IF(D55>=7,"Pasivo","Detractor")) -> Pasivo | F55: 4 | G55: 4 | H55: Rapidez del trámite | I55: 1) Buen trato del personal cuando atiende | J55: Buena predisposición del personal, a pesar de la demora del sistema.

Sheet Indicadores
A1: Indicadores de Experiencia del Ciudadano
A2: Parte se calcula automáticamente desde 'Reseñas y Encuesta'; NPS/CSAT desde 'Respuestas Encuesta'
A3: ⚠ El NPS y el CSAT se calculan automáticamente a partir de las 50 respuestas (datos de prueba/ficticios) de la pestaña 'Respuestas Encuesta'. Reemplazá esa base cuando tengas los datos reales.
A4: 1. Indicadores calculados a partir de reseñas (Google Maps + Instagram)
A6: Indicador | B6: Resultado | C6: ¿Qué mide? | D6: Cómo interpretar el resultado obtenido
A7: Cantidad de reseñas relevadas | B7: =COUNTA('Reseñas y Encuesta'!H5:H17) -> 13 | C7: Cantidad total de reseñas de Google Maps e Instagram registradas en la pestaña 'Reseñas y Encuesta'. | D7: —
A8: Calificación promedio (solo reseñas con estrellas) | B8: =AVERAGE('Reseñas y Encuesta'!D5:D17) -> 2.7272727 | C8: Promedio de estrellas (escala 1 a 5) de las reseñas que incluyen calificación numérica. | D8: =IF(B8>=4.5,"Excelente: la percepción general es muy positiva.",IF(B8>=4,"Muy buena, aunque con margen de mejora.",IF(B8>=3,"Regular: hay señales de insatisfacción relevantes.","Crítica: predominan las experiencias negativas."))) & " Resultado actual: " & TEXT(B8,"0.0") & "/5." -> Crítica: predominan las experiencias negativas. Resultado actual: 2.7/5.
A9: % Reseñas positivas | B9: =COUNTIF('Reseñas y Encuesta'!H5:H17,"Positivo")/COUNTA('Reseñas y Encuesta'!H5:H17) -> 0.23076923 | C9: Proporción de reseñas cuyo tono general fue clasificado como positivo en 'Reseñas y Encuesta'. | D9: =IF(B9>=0.6,"Alta: predominan las experiencias positivas.",IF(B9>=0.4,"Moderada.","Baja: conviene reforzar la comunicación de los puntos fuertes.")) & " Resultado actual: " & TEXT(B9,"0%") -> Baja: conviene reforzar la comunicación de los puntos fuertes. Resultado actual: 23%
A10: % Reseñas negativas | B10: =COUNTIF('Reseñas y Encuesta'!H5:H17,"Negativo")/COUNTA('Reseñas y Encuesta'!H5:H17) -> 0.61538462 | C10: Proporción de reseñas cuyo tono general fue clasificado como negativo en 'Reseñas y Encuesta'. | D10: =IF(B10>=0.5,"Alta: más de la mitad de la muestra es negativa (recordar que son reseñas construidas para ilustrar cada hallazgo, no una muestra real).",IF(B10>=0.25,"Moderada: hay puntos de fricción a atender.","Baja.")) & " Resultado actual: " & TEXT(B10,"0%") -> Alta: más de la mitad de la muestra es negativa (recordar que son reseñas construidas para ilustrar cada hallazgo, no una muestra real). Resultado actual: 62%
A11: % Reseñas mixtas | B11: =COUNTIF('Reseñas y Encuesta'!H5:H17,"Mixto")/COUNTA('Reseñas y Encuesta'!H5:H17) -> 0.15384615 | C11: Proporción de reseñas que combinan aspectos positivos y negativos en el mismo comentario. | D11: =IF(B11>=0.2,"Relevante: conviene revisar qué puntos de contacto generan esa ambivalencia.","Poco relevante.") & " Resultado actual: " & TEXT(B11,"0%") -> Poco relevante. Resultado actual: 15%
A13: Menciones por categoría — reseñas + encuesta (50 respuestas)
A14: Categoría | B14: Menciones en reseñas | C14: Menciones en encuesta | D14: Total combinado | E14: % del total combinado | F14: ¿Qué implica este hallazgo?
A15: 1) Buen trato del personal cuando atiende | B15: =COUNTIF('Reseñas y Encuesta'!G5:G17,A15) -> 4 | C15: =COUNTIF('Respuestas Encuesta'!I6:I55,A15) -> 17 | D15: =B15+C15 -> 21 | E15: =D15/63 -> 0.33333333 | F15: El personal de atención, cuando atiende, genera confianza gracias a un trato cálido y claro.
A16: 2) Turnos escasos y demoras | B16: =COUNTIF('Reseñas y Encuesta'!G5:G17,A16) -> 2 | C16: =COUNTIF('Respuestas Encuesta'!I6:I55,A16) -> 6 | D16: =B16+C16 -> 8 | E16: =D16/63 -> 0.12698413 | F16: Los turnos disponibles son escasos, generando demoras de hasta 45 días en temporada alta.
A17: 3) Errores en los datos del documento emitido | B17: =COUNTIF('Reseñas y Encuesta'!G5:G17,A17) -> 2 | C17: =COUNTIF('Respuestas Encuesta'!I6:I55,A17) -> 10 | D17: =B17+C17 -> 12 | E17: =D17/63 -> 0.19047619 | F17: Existen errores en los datos de los documentos emitidos, que obligan a reiniciar el trámite.
A18: 4) Información de requisitos poco clara o desactualizada | B18: =COUNTIF('Reseñas y Encuesta'!G5:G17,A18) -> 2 | C18: =COUNTIF('Respuestas Encuesta'!I6:I55,A18) -> 5 | D18: =B18+C18 -> 7 | E18: =D18/63 -> 0.11111111 | F18: La información de requisitos en los canales digitales está desactualizada o es inconsistente entre delegaciones.
A19: 5) Falta de un canal 100% digital | B19: =COUNTIF('Reseñas y Encuesta'!G5:G17,A19) -> 3 | C19: =COUNTIF('Respuestas Encuesta'!I6:I55,A19) -> 8 | D19: =B19+C19 -> 11 | E19: =D19/63 -> 0.17460317 | F19: El trámite exige presencialidad en todas sus etapas, sin una alternativa 100% digital.
A22: 2. NPS (Net Promoter Score) — calculado desde 'Respuestas Encuesta' (n=50)
A23: ¿Qué mide? La disposición a recomendar el trámite: resulta de restar el % de detractores al % de promotores (rango de -100% a 100%), a partir de la pregunta '¿qué probabilidad hay de que lo recomiendes?' (escala 0 a 10).
A25: Concepto | B25: Cantidad de respuestas | C25: % sobre el total | D25: ¿Qué significa este grupo?
A26: Promotores (calificación 9-10) | B26: =COUNTIF('Respuestas Encuesta'!E6:E55,"Promotor") -> 15 | C26: =IFERROR(B26/SUM($B$26:$B$28),0) -> 0.3 | D26: Ciudadanos conformes con el trámite: probablemente lo describan como una buena experiencia si se lo preguntan.
A27: Pasivos (calificación 7-8) | B27: =COUNTIF('Respuestas Encuesta'!E6:E55,"Pasivo") -> 15 | C27: =IFERROR(B27/SUM($B$26:$B$28),0) -> 0.3 | D27: Ciudadanos que resolvieron el trámite pero con reservas: no lo destacarían ni lo criticarían activamente.
A28: Detractores (calificación 0-6) | B28: =COUNTIF('Respuestas Encuesta'!E6:E55,"Detractor") -> 20 | C28: =IFERROR(B28/SUM($B$26:$B$28),0) -> 0.4 | D28: Ciudadanos insatisfechos: es probable que hablen mal del trámite o del organismo con otros vecinos.
A29: Total de respuestas | B29: =SUM(B26:B28) -> 50 | D29: Tamaño de la muestra (n) sobre la que se calculan los porcentajes de arriba: cuanto mayor sea, más confiable es el resultado.
A31: NPS = % Promotores − % Detractores | B31: =IF(B29=0,"Cargar datos",(B26-B28)/B29) -> -0.1 | C31: =IF(ISNUMBER(B31),IF(B31>=0.7,"Excelente (nivel de clase mundial).",IF(B31>=0.3,"Muy bueno.",IF(B31>=0,"Aceptable, con oportunidades de mejora.","Crítico: predominan los detractores."))) & " Resultado actual: " & TEXT(B31,"0%") & " | Escala de referencia: menor a 0% necesita mejorar · 0%-30% bueno · 30%-70% muy bueno · mayor a 70% excelente.","Cargar los datos de la encuesta para calcular el NPS.") -> Crítico: predominan los detractores. Resultado actual: -10% | Escala de referencia: menor a 0% necesita mejorar · 0%-30% bueno · 30%-70% muy bueno · mayor a 70% excelente.
A33: 3. CSAT (Satisfacción, escala 1-5) — calculado desde 'Respuestas Encuesta' (n=50)
A34: ¿Qué mide? El % de encuestados satisfechos: quienes calificaron el trámite con 4 o 5 sobre 5. El benchmark habitual en servicios de atención ciudadana ronda el 80%.
A36: Calificación | B36: Cantidad de respuestas
A37: 5 | B37: =COUNTIF('Respuestas Encuesta'!F6:F55,A37) -> 11
A38: 4 | B38: =COUNTIF('Respuestas Encuesta'!F6:F55,A38) -> 10
A39: 3 | B39: =COUNTIF('Respuestas Encuesta'!F6:F55,A39) -> 17
A40: 2 | B40: =COUNTIF('Respuestas Encuesta'!F6:F55,A40) -> 7
A41: 1 | B41: =COUNTIF('Respuestas Encuesta'!F6:F55,A41) -> 5
A42: CSAT (% calificaciones 4 y 5) | B42: =IF(SUM(B37:B41)=0,"Cargar datos",(B37+B38)/SUM(B37:B41)) -> 0.42 | C42: =IF(ISNUMBER(B42),IF(B42>=0.8,"Alto: en línea o por encima del benchmark habitual de 80% en atención ciudadana.",IF(B42>=0.6,"Aceptable, aunque por debajo del benchmark habitual de 80%.","Bajo: conviene priorizar acciones correctivas.")) & " Resultado actual: " & TEXT(B42,"0%"),"Cargar los datos de la encuesta para calcular el CSAT.") -> Bajo: conviene priorizar acciones correctivas. Resultado actual: 42%

Sheet Customer Journey Map
A1: Customer Journey Map (As Is) — Ciudadano que Solicita una Partida de Nacimiento
A2: Estado actual del recorrido, con detalle por subetapa | DRCyD (caso ficticio) | trámite: Emisión de Partida de Nacimiento
A4: Etapa | B4: 1. Información y requisitos | D4: 2. Solicitud del trámite | F4: 3. Presentación en sede | H4: 4. Emisión y entrega | J4: 5. Posentrega
A5: Subetapa | B5: a) Búsqueda de información sobre requisitos | C5: b) Consulta de dudas | D5: a) Solicitud de turno | E5: b) Preparación de la documentación | F5: a) Llegada y espera en la sede | G5: b) Atención en ventanilla / verificación | H5: a) Procesamiento y emisión | I5: b) Entrega del documento | J5: a) Uso del documento | K5: b) Percepción y feedback
A6: Descripción de la etapa | B6: Momento en que el ciudadano busca información sobre los requisitos del trámite y resuelve dudas antes de iniciarlo. | D6: El ciudadano solicita un turno y reúne la documentación necesaria para presentarse. | F6: El ciudadano viaja hasta la sede, espera y es atendido en ventanilla para presentar su documentación. | H6: El organismo procesa la solicitud, emite el documento y lo entrega al ciudadano. | J6: Después de recibir el documento, el ciudadano lo usa, y su percepción general del organismo se consolida.
A7: Touchpoints | B7: Web institucional, boca a boca de vecinos, delegación municipal | C7: Teléfono de la sede, redes sociales del organismo | D7: Sistema de turnos (telefónico o presencial), sede | E7: DNI, formularios, fotocopias | F7: Sede central o delegación, sala de espera | G7: Ventanilla, personal de mesa de entradas | H7: Sistema interno del organismo, archivo/base de datos registral | I7: Ventanilla de entrega, documento físico | J7: Institución donde presenta el documento (escuela, banco, etc.) | K7: Google Maps, encuesta de satisfacción
A8: Acciones del ciudadano | B8: Busca en la web o pregunta a conocidos qué documentación necesita para el trámite | C8: Llama o escribe para confirmar dudas puntuales antes de ir | D8: Solicita un turno para iniciar el trámite | E8: Reúne la documentación requerida antes de presentarse | F8: Viaja hasta la sede (a veces varias horas) y espera su turno | G8: Presenta la documentación y es atendido por un empleado | H8: Espera a que se procese y emita el documento (5 a 10 días hábiles) | I8: Retira el documento, verificando que los datos sean correctos | J8: Presenta el documento para el trámite que lo motivó originalmente | K8: Deja una reseña o responde una encuesta sobre su experiencia
A9: Pensamientos y emociones | B9: Incertidumbre: "¿esto que encontré está actualizado?" | C9: Necesita confirmar para no perder el viaje en vano | D9: Ansiedad si la fecha disponible está muy lejos de cuando necesita el documento | E9: Duda sobre si tiene todo lo necesario, dado que la información no siempre es clara | F9: Frustración por el tiempo y el costo de viajar, sobre todo si vive lejos | G9: Alivio si el trato es cálido y claro, aunque haya tardado en llegar a este punto | H9: Espera pasiva, sin visibilidad de en qué etapa está su trámite | I9: Expectativa de que todo esté bien después de tanta espera | J9: Gran frustración si descubre un error recién en este momento, porque implica reiniciar el trámite | K9: Reconoce el buen trato del personal, pero la falta de digitalización pesa más en la valoración general
A10: Puntos de dolor | B10: Información desactualizada o inconsistente entre lo que dice la web y lo que piden en la sede | C10: Consultas por redes sociales sobre requisitos sin respuesta | D10: Turnos disponibles a 45 días, insuficientes frente a la demanda en temporada alta | E10: Descubre en la sede que le falta un requisito no informado correctamente | F10: No existe forma de evitar la presencialidad, incluso para quienes viven a horas de distancia | G10: La calidad de la atención depende de la persona que atienda ese día | H10: Sin sistema de seguimiento online del estado del trámite | I10: Errores en los datos del documento (fecha de nacimiento, nombres mal tipeados) | J10: Si el error se detecta tarde, hay que reiniciar todo el proceso de emisión | K10: La percepción general del organismo se ve afectada aunque la atención individual haya sido buena
A11: Oportunidades | B11: Actualizar y centralizar la información de requisitos en un único canal oficial confiable | C11: Designar un canal digital de consultas con tiempo de respuesta definido | D11: Ampliar la disponibilidad de turnos o habilitar un canal 100% online para iniciar el trámite sin turno presencial | E11: Checklist descargable y validado de requisitos según el tipo de trámite | F11: Habilitar el inicio del trámite 100% online para reducir o eliminar la necesidad de viajar | G11: Sostener y estandarizar la buena atención que ya se percibe, como base de la confianza institucional | H11: Implementar seguimiento online del estado del trámite (como un número de pedido) | I11: Doble verificación de datos antes de la impresión/emisión final | J11: Validación de datos con el ciudadano antes de la emisión final (confirmar datos por escrito) | K11: Comunicar avances del proyecto de digitalización para sostener la confianza mientras se implementa
A12: Evidencia / Fuente | B12: Reseñas sobre web con información vieja y requisitos distintos a los publicados (Hallazgo 4) | C12: Comentarios de Instagram sin respuesta sobre requisitos (Hallazgo 4) | D12: Reseña sobre turno a 45 días, no llegaba a la fecha necesaria (Hallazgo 2) | E12: Reseñas sobre requisitos poco claros (Hallazgo 4) | F12: Reseña sobre viajar 3 horas en auto por no poder gestionar el trámite a distancia (Hallazgo 5) | G12: Reseñas positivas sobre el trato del personal (Hallazgo 1) | H12: Estado actual del proceso: sin opción de seguimiento (contexto del organismo) | I12: Reseñas sobre errores de tipeo en la partida (Hallazgo 3) | J12: Reseña sobre tener que rehacer todo el trámite por un error de fecha (Hallazgo 3) | K12: Cita "el problema es el sistema, no la gente" (Hallazgo 1 / Hallazgo 5)

Sheet Customer Journey Map (To Be)
A1: Customer Journey Map (To Be) — Ciudadano que Solicita una Partida de Nacimiento
A2: Estado deseado del recorrido una vez digitalizado el trámite | DRCyD (caso ficticio)
A4: Etapa | B4: 1. Información y requisitos | D4: 2. Solicitud del trámite | F4: 3. Presentación en sede | H4: 4. Emisión y entrega | J4: 5. Posentrega
A5: Subetapa | B5: a) Búsqueda de información sobre requisitos | C5: b) Consulta de dudas | D5: a) Solicitud de turno | E5: b) Preparación de la documentación | F5: a) Llegada y espera en la sede | G5: b) Atención en ventanilla / verificación | H5: a) Procesamiento y emisión | I5: b) Entrega del documento | J5: a) Uso del documento | K5: b) Percepción y feedback
A6: Descripción de la etapa | B6: El ciudadano encuentra información clara, centralizada y actualizada sobre los requisitos, y resuelve sus dudas por un canal digital con respuesta rápida. | D6: El ciudadano inicia el trámite 100% online, sin necesidad de turno presencial ni de reunir documentación física innecesaria. | F6: El trámite se completa mayormente a distancia; la presencialidad, si es necesaria, es breve y bien coordinada. | H6: El ciudadano recibe el documento digital con firma electrónica y código QR de validación, con seguimiento del estado del trámite en todo momento. | J6: La confianza institucional se sostiene con datos correctos desde el inicio y una comunicación transparente del avance del proyecto de digitalización.
A7: Touchpoints (mejorados) | B7: Portal único de trámites del organismo, con requisitos actualizados y validados | C7: Canal digital de consultas (WhatsApp oficial o chat del portal) | D7: Plataforma online de solicitud, sin necesidad de turno presencial | E7: Checklist digital interactivo dentro de la plataforma | F7: Sede, con cita puntual y breve si el trámite lo requiere | G7: Ventanilla o canal digital, personal capacitado en el nuevo sistema | H7: Sistema con seguimiento online del estado del trámite (número de pedido) | I7: Documento digital con firma electrónica y código QR de validación | J7: Verificación online del documento por parte de terceros (QR) | K7: Encuesta de satisfacción digital, canales de reseña
A8: Acciones del ciudadano | B8: Encuentra toda la información necesaria en un solo lugar, sin dudas | C8: Recibe respuesta a sus dudas puntuales en pocas horas | D8: Inicia el trámite completo desde su casa, cargando la documentación digitalmente | E8: Carga la documentación siguiendo un checklist validado, sin sorpresas | F8: Si necesita ir, lo hace en un horario acotado y sin esperas largas | G8: Es atendido con la misma calidez de siempre, ahora también en el canal digital | H8: Consulta el estado de su trámite en cualquier momento desde el portal | I8: Recibe el documento digital, lo descarga y verifica sus datos antes de usarlo | J8: Presenta el documento digital, que la institución receptora puede validar online | K8: Valora la experiencia general, incluyendo la reducción de tiempos y viajes
A9: Pensamientos y emociones (esperados) | B9: Confianza en la información oficial | C9: Tranquilidad para avanzar con el trámite | D9: Alivio de no depender de la disponibilidad de turnos presenciales | E9: Seguridad de que no le va a faltar nada | F9: Sensación de que el viaje, si lo hay, tiene sentido y es breve | G9: Mantiene la confianza en el trato humano, incluso con el trámite digitalizado | H9: Tranquilidad de tener visibilidad del proceso | I9: Confianza en que el documento es válido y los datos son correctos | J9: Seguridad de que el documento va a ser aceptado sin objeciones | K9: Percepción de un organismo que mejora y escucha
A10: Mejora implementada | B10: Actualización y centralización de la información de requisitos en el portal único de trámites | C10: Canal digital de consultas con tiempo de respuesta definido (SLA) | D10: Habilitación del inicio del trámite 100% online | E10: Checklist digital interactivo según el tipo de trámite, con validación automática de archivos | F10: Reducción de los pasos que requieren presencialidad al mínimo indispensable | G10: Capacitación del personal para sostener la calidad de atención en los nuevos canales digitales | H10: Implementación de seguimiento online del estado del trámite | I10: Doble verificación de datos con el ciudadano antes de la emisión final + firma digital y QR de validación | J10: Validación online del documento mediante código QR, interoperable con otros organismos | K10: Comunicación activa de los avances del proyecto de digitalización y canal de feedback ciudadano
A11: Resultado esperado / KPI | B11: % de consultas telefónicas por dudas de requisitos (objetivo: reducción) | C11: Tiempo de respuesta promedio a consultas digitales | D11: % de trámites iniciados online (objetivo: mayoría del volumen) | E11: % de trámites rechazados por documentación incompleta (objetivo: reducción) | F11: % de trámites que no requieren presencialidad | G11: Nivel de satisfacción con la atención (encuesta), en canal presencial y digital | H11: Tiempo promedio de emisión (objetivo: menor a 5 días hábiles) | I11: Tasa de errores en documentos emitidos (objetivo: reducción significativa) | J11: % de documentos digitales aceptados sin observaciones por terceros | K11: NPS / CSAT del trámite digitalizado vs. el proceso presencial anterior
A12: Vinculación con hallazgo (As Is) | B12: Resuelve el Hallazgo 4 (información poco clara o desactualizada) | C12: Resuelve el Hallazgo 4 (información poco clara o desactualizada) | D12: Resuelve los Hallazgos 2 y 5 (turnos escasos / falta de canal digital) | E12: Resuelve el Hallazgo 4 (información poco clara o desactualizada) | F12: Resuelve el Hallazgo 5 (falta de un canal 100% digital) | G12: Refuerza el Hallazgo 1 (buen trato del personal) | H12: Mejora el tiempo total del trámite (objetivo del proyecto) | I12: Resuelve el Hallazgo 3 (errores en los datos del documento) | J12: Resuelve el Hallazgo 3 y da sostenibilidad a la digitalización | K12: Refuerza el Hallazgo 1 y da cierre al Hallazgo 5

Sheet Service Blueprint
A1: Service Blueprint — Ciudadano que Solicita una Partida de Nacimiento
A2: Complementa el Customer Journey Map con la vista interna del servicio: frontstage, backstage y procesos de soporte | DRCyD (caso ficticio)
A4: Etapa | B4: 1. Información y requisitos | D4: 2. Solicitud del trámite | F4: 3. Presentación en sede | H4: 4. Emisión y entrega | J4: 5. Posentrega
A5: Subetapa | B5: a) Búsqueda de información sobre requisitos | C5: b) Consulta de dudas | D5: a) Solicitud de turno | E5: b) Preparación de la documentación | F5: a) Llegada y espera en la sede | G5: b) Atención en ventanilla / verificación | H5: a) Procesamiento y emisión | I5: b) Entrega del documento | J5: a) Uso del documento | K5: b) Percepción y feedback
A6: Evidencia física | B6: Portal web institucional, folletería en la sede | C6: Redes sociales del organismo, línea telefónica | D6: Sistema de turnos, sede | E6: Formularios, checklist de requisitos (si existe) | F6: Sede, sala de espera, sistema de numeración | G6: Ventanilla, documentación presentada | H6: Sistema interno, archivo registral | I6: Documento físico, ventanilla de entrega | J6: Documento presentado ante terceros (escuela, banco, etc.) | K6: Reseña en Google Maps, encuesta de satisfacción
A7: Acciones del ciudadano | B7: Busca en la web o pregunta a conocidos qué documentación necesita para el trámite | C7: Llama o escribe para confirmar dudas puntuales antes de ir | D7: Solicita un turno para iniciar el trámite | E7: Reúne la documentación requerida antes de presentarse | F7: Viaja hasta la sede (a veces varias horas) y espera su turno | G7: Presenta la documentación y es atendido por un empleado | H7: Espera a que se procese y emita el documento (5 a 10 días hábiles) | I7: Retira el documento, verificando que los datos sean correctos | J7: Presenta el documento para el trámite que lo motivó originalmente | K7: Deja una reseña o responde una encuesta sobre su experiencia
A8: ▬▬▬ LÍNEA DE INTERACCIÓN ▬▬▬
A9: Frontstage (personal de contacto directo) | B9: Sin interacción humana directa en este momento | C9: Personal de atención telefónica o community manager responde consultas | D9: Personal de mesa de entradas asigna el turno | E9: Sin interacción humana directa en este momento | F9: Personal de recepción organiza la espera | G9: Empleado de mesa de entradas verifica la documentación y atiende al ciudadano | H9: Sin interacción directa con el ciudadano en este momento | I9: Empleado entrega el documento y responde consultas finales | J9: Sin interacción directa del organismo en este momento | K9: Sin respuesta institucional sistemática a las reseñas (actualmente)
A10: ▬▬▬ LÍNEA DE VISIBILIDAD ▬▬▬
A11: Backstage (personal sin contacto directo) | B11: Actualización de contenidos del portal, coordinación entre delegaciones para unificar requisitos | C11: Gestión de contenidos de redes, capacitación del personal de atención telefónica | D11: Gestión de la agenda de turnos según capacidad operativa de cada delegación | E11: Definición y actualización de los requisitos según normativa vigente | F11: Gestión de la afluencia de público según horarios de mayor demanda | G11: Carga de datos en el sistema registral | H11: Procesamiento administrativo y validación de los datos para la emisión del documento | I11: Impresión y control de calidad del documento antes de la entrega | J11: Sin proceso interno relevante (el documento ya fue emitido) | K11: Sin proceso de gestión de reputación online sistematizado
A12: ▬▬▬ LÍNEA DE INTERACCIÓN INTERNA ▬▬▬
A13: Procesos de soporte (sistemas y proveedores) | B13: CMS del portal de trámites, mesa de ayuda telefónica | C13: Sistema de mensajería / redes sociales institucionales | D13: Sistema de gestión de turnos | E13: Normativa del Registro Civil, formularios oficiales | F13: Sistema de gestión de filas/turnos en sede | G13: Sistema registral interno, base de datos del Registro Civil | H13: Sistema registral, archivo histórico de actas | I13: Sistema de impresión, checklist de control de calidad (si existe) | J13: — | K13: Google Business Profile (si existe), sistema de encuestas
A14: Punto de fallo potencial (riesgo) | B14: Información desactualizada entre delegaciones y el portal central (Hallazgo 4) | C14: Consultas por redes sin respuesta (Hallazgo 4) | D14: Capacidad de turnos insuficiente frente a la demanda estacional (Hallazgo 2) | E14: Requisitos mal comunicados generan trámites incompletos (Hallazgo 4) | F14: Viajes largos para quienes viven lejos de la sede, sin alternativa a distancia (Hallazgo 5) | G14: La calidad de la atención depende de la persona que atienda ese día (Hallazgo 1) | H14: Sin visibilidad del estado del trámite para el ciudadano durante este proceso | I14: Errores de tipeo en los datos del documento emitido (Hallazgo 3) | J14: Si el error se detecta tarde, el ciudadano debe reiniciar todo el trámite de emisión (Hallazgo 3) | K14: Sin protocolo de respuesta, se pierde la oportunidad de mostrar mejoras y sostener la confianza institucional (Hallazgo 1 / Hallazgo 5)
A16: Referencias: por encima de la línea de interacción, lo que el ciudadano hace y ve (front stage). Entre la línea de visibilidad y la de interacción interna, lo que hace el personal sin contacto directo (back stage). Debajo, los sistemas y proveedores que sostienen el servicio.

Sheet Insights y Oportunidades
A1: Síntesis de Hallazgos, Insights y Priorización
A2: DRCyD (caso ficticio) — misma metodología aplicada a Clínica Bermejo, Café Aurora y Hotel Costa Azul
A4: # | B4: Hallazgo | C4: Insight | D4: Etapa del CJM más afectada | E4: Impacto (Alto/Medio/Bajo) | F4: Prioridad sugerida
A5: 1 | B5: El personal de atención, cuando atiende, genera confianza gracias a un trato cálido y claro. | C5: La percepción positiva de la atención humana coexiste con una fuerte frustración por las limitaciones del sistema, lo que indica que el problema es estructural, no de las personas. | D5: Atención en ventanilla / verificación | E5: Alto | F5: Media
A6: 2 | B6: Los turnos disponibles son escasos, generando demoras de hasta 45 días en temporada alta. | C6: La capacidad operativa actual no acompaña los picos de demanda estacional (inicio de clases), afectando a quienes tienen plazos externos que cumplir. | D6: Solicitud de turno | E6: Alto | F6: Alta
A7: 3 | B7: Existen errores en los datos de los documentos emitidos, que obligan a reiniciar el trámite. | C7: La falta de una instancia de verificación con el ciudadano antes de la emisión final genera un costo alto y evitable, tanto para el ciudadano como para el organismo. | D7: Entrega del documento | E7: Alto | F7: Alta
A8: 4 | B8: La información de requisitos en los canales digitales está desactualizada o es inconsistente entre delegaciones. | C8: La falta de un canal único y confiable de información genera viajes en vano y sobrecarga los canales de consulta telefónica. | D8: Búsqueda de información | E8: Medio | F8: Media
A9: 5 | B9: El trámite exige presencialidad en todas sus etapas, sin una alternativa 100% digital. | C9: Esta es la causa raíz del proyecto de digitalización: eliminar la presencialidad innecesaria reduciría drásticamente el costo del trámite para el ciudadano, especialmente en el interior de la provincia. | D9: Llegada y espera en la sede | E9: Alto | F9: Alta
