Workbook

Sheet Guía
A1: Hotel Costa Azul — Perfil de Huésped y Experiencia
A4: Cómo usar este archivo
A5: Pestaña | B5: Contenido | C5: Qué hacer
A6: Buyer Persona | B6: Ficha de Marcela Fontana, persona ficticia que representa al segmento de familias que viajan en temporada alta: datos generales, objetivos, frustraciones (ligadas a los hallazgos), motivaciones y factores de decisión. | C6: Usar como referencia rápida de 'para quién' se diseña el resto del archivo (reseñas, CJM, blueprint).
A7: Reseñas y Encuesta | B7: Reseñas ficticias de Google Maps y Booking.com, construidas para ilustrar 5 hallazgos típicos de un hotel pequeño familiar, y agregados de la encuesta (NPS, CSAT, CES) calculados desde 'Respuestas Encuesta'. | C7: Las reseñas ya están cargadas. Los agregados de encuesta se recalculan solos cuando actualices la base de respuestas.
A8: Respuestas Encuesta | B8: Base de 50 respuestas individuales de una encuesta exploratoria (dato de prueba/ficticio): NPS, CSAT, CES, aspecto valorado, categoría asociada y comentario. | C8: Reemplazar estas 50 filas por datos reales cuando existan; el resto del archivo se recalcula automáticamente.
A9: Indicadores | B9: Métricas calculadas automáticamente a partir de las reseñas y de las 50 respuestas de encuesta: rating promedio, % positivas/negativas, menciones por categoría, NPS y CSAT, cada uno con su definición e interpretación del resultado obtenido. | C9: No requiere carga manual: todo se recalcula solo desde 'Reseñas y Encuesta' y 'Respuestas Encuesta'.
A10: Customer Journey Map | B10: Mapa As Is de las 5 etapas / 10 subetapas del recorrido del huésped: descripción de cada etapa, touchpoints, acciones, emociones, dolores y oportunidades por subetapa. | C10: Base para trabajar en clase o ajustar con el grupo. Cada columna cita la evidencia de la que sale (reseña / hallazgo).
A11: Customer Journey Map (To Be) | B11: Misma estructura que el As Is, pero con el recorrido deseado: touchpoints mejorados, emociones esperadas, la mejora que resuelve cada dolor y el KPI para medirla. | C11: Usar para diseñar el plan de mejora; cada subetapa está vinculada al hallazgo del As Is que resuelve.
A12: Service Blueprint | B12: Complementa el CJM As Is con la vista interna del servicio: evidencia física, acciones del huésped, frontstage, backstage, procesos de soporte y punto de fallo potencial por subetapa. | C12: Usar para identificar qué proceso o sistema interno hay que ajustar para resolver cada punto de dolor del CJM.
A13: Insights y Oportunidades | B13: Síntesis de los 5 hallazgos con nivel de impacto y prioridad sugerida. | C13: Usar como tablero de priorización; el campo Prioridad tiene lista desplegable.
A15: Convención de colores
B16: Celda para completar (input del usuario / dato de la encuesta)
B17: Indicador o comentario en rango positivo
B18: Indicador o comentario en rango negativo / de atención

Sheet Buyer Persona
A1: Buyer Persona — Marcela Fontana (perfil ficticio)
A2: Representa al segmento de familias que viajan en temporada alta (Hotel Costa Azul)
A4: Nota: es un personaje ficticio construido para un caso también ficticio (Hotel Costa Azul). No representa a una huésped real.
A6: Datos generales
A7: Nombre (ficticio) | B7: Marcela Fontana
A8: Edad | B8: 41 años
A9: Ubicación | B9: CABA (viaja de vacaciones a la costa atlántica)
A10: Ocupación | B10: Contadora
A11: Estado civil | B11: Casada, dos hijos (10 y 7 años)
A12: Segmento | B12: Familias que viajan en temporada alta (mayor volumen y mayor exigencia de la estadía)
A13: Nivel socioeconómico | B13: Medio
A14: Rango etario del segmento | B14: 30 a 50 años (adultos a cargo de la reserva familiar)
A15: Frecuencia de visita | B15: Una vez por año, en enero, desde hace 3 temporadas
A17: "No busco lujos, busco que mis hijos estén cómodos y que nos traten bien."
A19: Bio / Contexto
A20: Marcela organiza las vacaciones familiares de enero con bastante anticipación: compara varios hoteles en Booking y Google antes de decidir, priorizando la relación precio-calidad y la cercanía a la playa por sobre el lujo. Eligió el Hotel Costa Azul hace tres años y volvió cada temporada desde entonces, en gran parte porque los dueños la reconocen y la hacen sentir parte de 'la familia del hotel'. Viaja con su marido y sus dos hijos, así que valora mucho que el check-in sea rápido y que la habitación esté lista y en buenas condiciones cuando llega, cansada del viaje y con los chicos impacientes.
A22: Objetivos
A23: • Encontrar un hotel con buena relación precio-calidad para vacacionar en familia.
A24: • Que la habitación esté limpia, cómoda y en buen estado (aire acondicionado funcionando en temporada alta).
A25: • Sentirse bien recibida, con un trato cálido y no solo transaccional.
A27: Frustraciones (ligadas a los hallazgos)
A28: Frustración | B28: Hallazgo relacionado
A29: El check-in a veces demora más de lo esperado, sobre todo en temporada alta. | B29: Hallazgo 2
A30: Alguna vez encontró problemas de mantenimiento (aire acondicionado, wifi) sin resolución rápida. | B30: Hallazgo 3
A31: Consultó por WhatsApp/Instagram antes de reservar y tardaron en responder. | B31: Hallazgo 4
A32: Sintió que el precio de temporada alta no se correspondía del todo con lo que recibía (ej. desayuno básico). | B32: Hallazgo 5
A34: Motivaciones
A35: • Vacaciones familiares tranquilas y sin sorpresas.
A36: • Trato cálido y personalizado (sentirse "como en familia").
A37: • Buenas reseñas de otras familias en Booking y Google Maps.
A39: Canales digitales que usa
A40: Booking.com (para comparar y reservar), Google Maps (para leer y dejar reseñas), Instagram y WhatsApp (para consultas puntuales antes de viajar).
A42: Factores de decisión (de mayor a menor peso)
A43: 1. Ubicación / cercanía a la playa.
A44: 2. Relación precio-calidad.
A45: 3. Trato cálido del personal y los dueños.
A46: 4. Comodidades específicas (pileta, desayuno) para los chicos.
A48: Relación con la marca Hotel Costa Azul
A49: A diferencia de la cafetería (donde la lealtad estaba más atada a la sucursal y la rutina) o la clínica (donde el vínculo era con un profesional puntual), en Hotel Costa Azul la lealtad de Marcela está fuertemente ligada a los dueños y al ritual de 'volver cada verano al mismo lugar'. Es un vínculo emocional de largo plazo, casi familiar, que representa la principal ventaja competitiva frente a hoteles de cadena, pero también un riesgo: si depende demasiado de personas puntuales, un cambio de gestión podría debilitarlo.

Sheet Reseñas y Encuesta
A1: Voz del Huésped — Reseñas (Google Maps / Booking.com) y Encuesta Exploratoria
A2: Segmento analizado: familias que viajan en temporada alta (caso ficticio, Hotel Costa Azul)
A4: # | B4: Fuente | C4: Autor | D4: Calificación (1-5) | E4: Antigüedad | F4: Comentario (resumen) | G4: Categoría / Hallazgo | H4: Sentimiento
A5: 1 | B5: Google Maps | C5: Marcela Fontana | D5: 5 | E5: Hace 3 meses | F5: El trato de los dueños es espectacular, se acuerdan de vos de un año a otro. Nos sentimos como en casa. | G5: 1) Calidez y trato del personal generan fidelidad | H5: Positivo
A6: 2 | B6: Google Maps | C6: Hernán Ríos | D6: 5 | E6: Hace 1 año | F6: La atención personalizada hace la diferencia, siempre atentos a cualquier pedido. | G6: 1) Calidez y trato del personal generan fidelidad | H6: Positivo
A7: 3 | B7: Booking.com | C7: Valeria Suárez | D7: 5 | E7: Hace 8 meses | F7: Un hotel chico pero con un trato enorme. Volvemos todos los años. | G7: 1) Calidez y trato del personal generan fidelidad | H7: Positivo
A8: 4 | B8: Google Maps | C8: Reseña sin nombre (cita textual) | E8: N/D | F8: "Es como visitar a la familia, no un hotel más." | G8: 1) Calidez y trato del personal generan fidelidad | H8: Positivo
A9: 5 | B9: Booking.com | C9: Nicolás Aguirre | D9: 3 | E9: Hace 5 meses | F9: La habitación bien, pero llegamos a las 13 y no estaba lista hasta las 15, sin aviso previo. | G9: 2) Demoras en check-in en temporada alta | H9: Mixto
A10: 6 | B10: Google Maps | C10: Pilar Escobar | D10: 2 | E10: Hace 2 meses | F10: El check-in tardó mucho, había una sola persona en recepción para atender a todos los que llegábamos juntos. | G10: 2) Demoras en check-in en temporada alta | H10: Negativo
A11: 7 | B11: Booking.com | C11: Tomás Ledesma | D11: 2 | E11: Hace 4 meses | F11: El aire acondicionado de la habitación no enfriaba bien y tardaron un día en solucionarlo. | G11: 3) Fallas de mantenimiento (AC, wifi, limpieza) | H11: Negativo
A12: 8 | B12: Google Maps | C12: Antonella Rivas | D12: 3 | E12: Hace 6 meses | F12: El wifi andaba muy mal en la habitación, tuvimos que trabajar desde el lobby. | G12: 3) Fallas de mantenimiento (AC, wifi, limpieza) | H12: Mixto
A13: 9 | B13: Instagram | C13: Varios usuarios (consultas espontáneas) | E13: N/D | F13: Varias preguntas por disponibilidad y tarifas de enero, sin respuesta visible en varios comentarios. | G13: 4) Oportunidad en consultas y reservas digitales | H13: Negativo
A14: 10 | B14: Booking.com | C14: Rocío Medina | D14: 4 | E14: Hace 3 meses | F14: Quise consultar por WhatsApp si tenían cochera y tardaron dos días en contestarme. | G14: 4) Oportunidad en consultas y reservas digitales | H14: Mixto
A15: 11 | B15: Google Maps | C15: Ezequiel Farías | D15: 2 | E15: Hace 1 mes | F15: El precio de temporada alta es muy caro para lo que ofrece, el desayuno es muy básico. | G15: 5) Percepción de precio-valor en temporada alta | H15: Negativo
A16: 12 | B16: Booking.com | C16: Carolina Núñez | D16: 3 | E16: Hace 2 meses | F16: Buena ubicación, pero sentí que la relación precio-calidad no es la mejor en enero. | G16: 5) Percepción de precio-valor en temporada alta | H16: Mixto
A17: 13 | B17: Google Maps | C17: Bautista Medina | D17: 5 | E17: Hace 7 meses | F17: Volvemos cada verano, el trato es único y eso vale más que cualquier detalle. | G17: 1) Calidez y trato del personal generan fidelidad | H17: Positivo
A19: Nota: reseñas 100% ficticias, redactadas para ilustrar 5 hallazgos típicos de un hotel pequeño familiar (Fuente simulada: Google Maps, Booking.com e Instagram). Las calificaciones en estrellas de Instagram no aplican (N/D).
A22: Encuesta exploratoria de percepción de huéspedes
A23: Los valores de abajo se calculan automáticamente a partir de las 50 respuestas cargadas en la pestaña 'Respuestas Encuesta' (dato de prueba/ficticio).
A25: # | B25: Pregunta de la encuesta | C25: Tipo de respuesta | D25: Respuesta / Valor | E25: Escala
A26: 1 | B26: ¿Con qué probabilidad recomendarías Hotel Costa Azul a un familiar o amigo? | C26: Numérica (NPS) | D26: =AVERAGE('Respuestas Encuesta'!D6:D55) -> 8.06 | E26: 0 a 10
A27: 2 | B27: ¿Cómo calificarías tu satisfacción general con la estadía? | C27: Numérica (CSAT) | D27: =AVERAGE('Respuestas Encuesta'!F6:F55) -> 3.76 | E27: 1 a 5
A28: 3 | B28: ¿Qué tan rápido fue el check-in? | C28: Numérica (CES simplificado) | D28: =AVERAGE('Respuestas Encuesta'!G6:G55) -> 3.46 | E28: 1 a 5
A29: 4 | B29: ¿Qué aspecto valorás más del hotel? | C29: Abierta / opción múltiple | D29: Ver detalle por respuesta en la pestaña 'Respuestas Encuesta', columna H | E29: Texto
A30: 5 | B30: ¿Qué mejorarías de tu estadía? | C30: Abierta | D30: Ver comentario y categoría asociada en la pestaña 'Respuestas Encuesta', columnas I-J | E30: Texto
A31: ⚠ Los promedios de arriba dependen de los datos de prueba (ficticios) cargados en 'Respuestas Encuesta'. Al reemplazar esa base por datos reales, estos valores se actualizan solos.

Sheet Respuestas Encuesta
A1: Respuestas Individuales — Encuesta Exploratoria de Huéspedes
A2: Base de 50 respuestas simuladas para practicar el cálculo de NPS, CSAT y CES (caso ficticio, Hotel Costa Azul)
A3: ⚠ Estas 50 respuestas son datos de prueba (ficticios), generados para completar el ejercicio. Reemplazar por datos reales cuando existan; el resto del archivo (pestañas 'Reseñas y Encuesta' e 'Indicadores') se recalcula solo.
A5: ID | B5: Fecha | C5: Canal | D5: NPS (0-10) | E5: Clasificación NPS | F5: CSAT (1-5) | G5: CES (1-5) | H5: Aspecto más valorado | I5: Categoría asociada (hallazgo) | J5: Comentario (resumen)
A6: R001 | B6: 46034 | C6: Formulario en el hotel | D6: 9 | E6: =IF(D6>=9,"Promotor",IF(D6>=7,"Pasivo","Detractor")) -> Promotor | F6: 5 | G6: 5 | H6: Limpieza y mantenimiento de la habitación | I6: 1) Calidez y trato del personal generan fidelidad | J6: Nos sentimos como en familia.
A7: R002 | B7: 46033 | C7: WhatsApp | D7: 9 | E7: =IF(D7>=9,"Promotor",IF(D7>=7,"Pasivo","Detractor")) -> Promotor | F7: 4 | G7: 4 | H7: Desayuno / servicios | I7: 4) Oportunidad en consultas y reservas digitales | J7: Pregunté por Instagram y no tuve respuesta.
A8: R003 | B8: 46034 | C8: Google Maps | D8: 8 | E8: =IF(D8>=9,"Promotor",IF(D8>=7,"Pasivo","Detractor")) -> Pasivo | F8: 4 | G8: 1 | H8: Trato del personal / dueños | I8: 2) Demoras en check-in en temporada alta | J8: Había mucha gente llegando junta y pocos empleados.
A9: R004 | B9: 46055 | C9: Formulario en el hotel | D9: 8 | E9: =IF(D9>=9,"Promotor",IF(D9>=7,"Pasivo","Detractor")) -> Pasivo | F9: 5 | G9: 2 | H9: Relación precio-valor | I9: 5) Percepción de precio-valor en temporada alta | J9: El precio de temporada alta es alto para lo que ofrece.
A10: R005 | B10: 46030 | C10: Google Maps | D10: 9 | E10: =IF(D10>=9,"Promotor",IF(D10>=7,"Pasivo","Detractor")) -> Promotor | F10: 5 | G10: 3 | H10: Limpieza y mantenimiento de la habitación | I10: Sin comentario asociado | J10: -
A11: R006 | B11: 46043 | C11: Google Maps | D11: 9 | E11: =IF(D11>=9,"Promotor",IF(D11>=7,"Pasivo","Detractor")) -> Promotor | F11: 3 | G11: 4 | H11: Trato del personal / dueños | I11: 1) Calidez y trato del personal generan fidelidad | J11: El trato de los dueños es único, se acuerdan de nosotros cada año.
A12: R007 | B12: 46071 | C12: Booking.com | D12: 8 | E12: =IF(D12>=9,"Promotor",IF(D12>=7,"Pasivo","Detractor")) -> Pasivo | F12: 4 | G12: 4 | H12: Otro | I12: 1) Calidez y trato del personal generan fidelidad | J12: El trato de los dueños es único, se acuerdan de nosotros cada año.
A13: R008 | B13: 46037 | C13: Google Maps | D13: 3 | E13: =IF(D13>=9,"Promotor",IF(D13>=7,"Pasivo","Detractor")) -> Detractor | F13: 3 | G13: 2 | H13: Otro | I13: 1) Calidez y trato del personal generan fidelidad | J13: La atención personalizada hace toda la diferencia.
A14: R009 | B14: 46030 | C14: WhatsApp | D14: 7 | E14: =IF(D14>=9,"Promotor",IF(D14>=7,"Pasivo","Detractor")) -> Pasivo | F14: 4 | G14: 4 | H14: Desayuno / servicios | I14: 3) Fallas de mantenimiento (AC, wifi, limpieza) | J14: Encontramos algunos detalles de limpieza para mejorar.
A15: R010 | B15: 46069 | C15: Formulario en el hotel | D15: 9 | E15: =IF(D15>=9,"Promotor",IF(D15>=7,"Pasivo","Detractor")) -> Promotor | F15: 5 | G15: 5 | H15: Limpieza y mantenimiento de la habitación | I15: 5) Percepción de precio-valor en temporada alta | J15: El precio de temporada alta es alto para lo que ofrece.
A16: R011 | B16: 46027 | C16: WhatsApp | D16: 7 | E16: =IF(D16>=9,"Promotor",IF(D16>=7,"Pasivo","Detractor")) -> Pasivo | F16: 3 | G16: 3 | H16: Otro | I16: Sin comentario asociado | J16: Ninguna observación puntual.
A17: R012 | B17: 46038 | C17: Google Maps | D17: 7 | E17: =IF(D17>=9,"Promotor",IF(D17>=7,"Pasivo","Detractor")) -> Pasivo | F17: 2 | G17: 3 | H17: Limpieza y mantenimiento de la habitación | I17: 5) Percepción de precio-valor en temporada alta | J17: El precio de temporada alta es alto para lo que ofrece.
... A55: R050 | B55: 46065 | C55: Formulario en el hotel | D55: 4 | E55: =IF(D55>=9,"Promotor",IF(D55>=7,"Pasivo","Detractor")) -> Detractor | F55: 2 | G55: 2 | H55: Relación precio-valor | I55: Sin comentario asociado | J55: Todo bien, sin comentarios.

Sheet Indicadores
A1: Indicadores de Experiencia del Huésped
A2: Parte se calcula automáticamente desde 'Reseñas y Encuesta'; NPS/CSAT desde 'Respuestas Encuesta'
A3: ⚠ El NPS y el CSAT se calculan automáticamente a partir de las 50 respuestas (datos de prueba/ficticios) de la pestaña 'Respuestas Encuesta'. Reemplazá esa base cuando tengas los datos reales.
A4: 1. Indicadores calculados a partir de reseñas (Google Maps + Booking.com)
A6: Indicador | B6: Resultado | C6: ¿Qué mide? | D6: Cómo interpretar el resultado obtenido
A7: Cantidad de reseñas relevadas | B7: =COUNTA('Reseñas y Encuesta'!H5:H17) -> 13 | C7: Cantidad total de reseñas de Google Maps y Booking.com registradas en la pestaña 'Reseñas y Encuesta'. | D7: —
A8: Calificación promedio (solo reseñas con estrellas) | B8: =AVERAGE('Reseñas y Encuesta'!D5:D17) -> 3.5454545 | C8: Promedio de estrellas (escala 1 a 5) de las reseñas que incluyen calificación numérica. | D8: =IF(B8>=4.5,"Excelente: la percepción general es muy positiva.",IF(B8>=4,"Muy buena, aunque con margen de mejora.",IF(B8>=3,"Regular: hay señales de insatisfacción relevantes.","Crítica: predominan las experiencias negativas."))) & " Resultado actual: " & TEXT(B8,"0.0") & "/5." -> Regular: hay señales de insatisfacción relevantes. Resultado actual: 3.5/5.
A9: % Reseñas positivas | B9: =COUNTIF('Reseñas y Encuesta'!H5:H17,"Positivo")/COUNTA('Reseñas y Encuesta'!H5:H17) -> 0.38461538 | C9: Proporción de reseñas cuyo tono general fue clasificado como positivo en 'Reseñas y Encuesta'. | D9: =IF(B9>=0.6,"Alta: predominan las experiencias positivas.",IF(B9>=0.4,"Moderada.","Baja: conviene reforzar la comunicación de los puntos fuertes.")) & " Resultado actual: " & TEXT(B9,"0%") -> Baja: conviene reforzar la comunicación de los puntos fuertes. Resultado actual: 38%
A10: % Reseñas negativas | B10: =COUNTIF('Reseñas y Encuesta'!H5:H17,"Negativo")/COUNTA('Reseñas y Encuesta'!H5:H17) -> 0.30769231 | C10: Proporción de reseñas cuyo tono general fue clasificado como negativo en 'Reseñas y Encuesta'. | D10: =IF(B10>=0.5,"Alta: más de la mitad de la muestra es negativa (recordar que son reseñas construidas para ilustrar cada hallazgo, no una muestra real).",IF(B10>=0.25,"Moderada: hay puntos de fricción a atender.","Baja.")) & " Resultado actual: " & TEXT(B10,"0%") -> Moderada: hay puntos de fricción a atender. Resultado actual: 31%
A11: % Reseñas mixtas | B11: =COUNTIF('Reseñas y Encuesta'!H5:H17,"Mixto")/COUNTA('Reseñas y Encuesta'!H5:H17) -> 0.30769231 | C11: Proporción de reseñas que combinan aspectos positivos y negativos en el mismo comentario. | D11: =IF(B11>=0.2,"Relevante: conviene revisar qué puntos de contacto generan esa ambivalencia.","Poco relevante.") & " Resultado actual: " & TEXT(B11,"0%") -> Relevante: conviene revisar qué puntos de contacto generan esa ambivalencia. Resultado actual: 31%
A13: Menciones por categoría — reseñas + encuesta (50 respuestas)
A14: Categoría | B14: Menciones en reseñas | C14: Menciones en encuesta | D14: Total combinado | E14: % del total combinado | F14: ¿Qué implica este hallazgo?
A15: 1) Calidez y trato del personal generan fidelidad | B15: =COUNTIF('Reseñas y Encuesta'!G5:G17,A15) -> 5 | C15: =COUNTIF('Respuestas Encuesta'!I6:I55,A15) -> 19 | D15: =B15+C15 -> 24 | E15: =D15/63 -> 0.38095238 | F15: La calidez y personalización del trato de los dueños genera fidelidad fuerte y visitas recurrentes año tras año.
A16: 2) Demoras en check-in en temporada alta | B16: =COUNTIF('Reseñas y Encuesta'!G5:G17,A16) -> 2 | C16: =COUNTIF('Respuestas Encuesta'!I6:I55,A16) -> 5 | D16: =B16+C16 -> 7 | E16: =D16/63 -> 0.11111111 | F16: En temporada alta, el check-in y la disponibilidad de la habitación generan demoras y frustración.
A17: 3) Fallas de mantenimiento (AC, wifi, limpieza) | B17: =COUNTIF('Reseñas y Encuesta'!G5:G17,A17) -> 2 | C17: =COUNTIF('Respuestas Encuesta'!I6:I55,A17) -> 2 | D17: =B17+C17 -> 4 | E17: =D17/63 -> 0.063492063 | F17: Existen fallas de mantenimiento (aire acondicionado, wifi) sin resolución rápida durante la estadía.
A18: 4) Oportunidad en consultas y reservas digitales | B18: =COUNTIF('Reseñas y Encuesta'!G5:G17,A18) -> 2 | C18: =COUNTIF('Respuestas Encuesta'!I6:I55,A18) -> 3 | D18: =B18+C18 -> 5 | E18: =D18/63 -> 0.079365079 | F18: Las consultas de reserva por WhatsApp/Instagram no siempre reciben respuesta rápida.
A19: 5) Percepción de precio-valor en temporada alta | B19: =COUNTIF('Reseñas y Encuesta'!G5:G17,A19) -> 2 | C19: =COUNTIF('Respuestas Encuesta'!I6:I55,A19) -> 8 | D19: =B19+C19 -> 10 | E19: =D19/63 -> 0.15873016 | F19: Parte de los huéspedes percibe que el precio de temporada alta no se corresponde con la calidad/servicios ofrecidos.
A22: 2. NPS (Net Promoter Score) — calculado desde 'Respuestas Encuesta' (n=50)
A23: ¿Qué mide? La disposición a recomendar Hotel Costa Azul: resulta de restar el % de detractores al % de promotores (rango de -100% a 100%), a partir de la pregunta '¿qué probabilidad hay de que nos recomiendes?' (escala 0 a 10).
A25: Concepto | B25: Cantidad de respuestas | C25: % sobre el total | D25: ¿Qué significa este grupo?
A26: Promotores (calificación 9-10) | B26: =COUNTIF('Respuestas Encuesta'!E6:E55,"Promotor") -> 30 | C26: =IFERROR(B26/SUM($B$26:$B$28),0) -> 0.6 | D26: Huéspedes entusiastas y leales: probablemente recomienden el hotel de forma espontánea y vuelvan la próxima temporada.
A27: Pasivos (calificación 7-8) | B27: =COUNTIF('Respuestas Encuesta'!E6:E55,"Pasivo") -> 12 | C27: =IFERROR(B27/SUM($B$26:$B$28),0) -> 0.24 | D27: Huéspedes conformes pero poco entusiastas: vulnerables a probar otros hoteles de la zona.
A28: Detractores (calificación 0-6) | B28: =COUNTIF('Respuestas Encuesta'!E6:E55,"Detractor") -> 8 | C28: =IFERROR(B28/SUM($B$26:$B$28),0) -> 0.16 | D28: Huéspedes insatisfechos: pueden dañar la reputación del hotel con comentarios negativos.
A29: Total de respuestas | B29: =SUM(B26:B28) -> 50 | D29: Tamaño de la muestra (n) sobre la que se calculan los porcentajes de arriba: cuanto mayor sea, más confiable es el resultado.
A31: NPS = % Promotores − % Detractores | B31: =IF(B29=0,"Cargar datos",(B26-B28)/B29) -> 0.44 | C31: =IF(ISNUMBER(B31),IF(B31>=0.7,"Excelente (nivel de clase mundial).",IF(B31>=0.3,"Muy bueno.",IF(B31>=0,"Aceptable, con oportunidades de mejora.","Crítico: predominan los detractores."))) & " Resultado actual: " & TEXT(B31,"0%") & " | Escala de referencia: menor a 0% necesita mejorar · 0%-30% bueno · 30%-70% muy bueno · mayor a 70% excelente.","Cargar los datos de la encuesta para calcular el NPS.") -> Muy bueno. Resultado actual: 44% | Escala de referencia: menor a 0% necesita mejorar · 0%-30% bueno · 30%-70% muy bueno · mayor a 70% excelente.
A33: 3. CSAT (Satisfacción, escala 1-5) — calculado desde 'Respuestas Encuesta' (n=50)
A34: ¿Qué mide? El % de encuestados satisfechos: quienes calificaron su estadía con 4 o 5 sobre 5. El benchmark habitual en hotelería ronda el 80%.
A36: Calificación | B36: Cantidad de respuestas
A37: 5 | B37: =COUNTIF('Respuestas Encuesta'!F6:F55,A37) -> 13
A38: 4 | B38: =COUNTIF('Respuestas Encuesta'!F6:F55,A38) -> 22
A39: 3 | B39: =COUNTIF('Respuestas Encuesta'!F6:F55,A39) -> 7
A40: 2 | B40: =COUNTIF('Respuestas Encuesta'!F6:F55,A40) -> 6
A41: 1 | B41: =COUNTIF('Respuestas Encuesta'!F6:F55,A41) -> 2
A42: CSAT (% calificaciones 4 y 5) | B42: =IF(SUM(B37:B41)=0,"Cargar datos",(B37+B38)/SUM(B37:B41)) -> 0.7 | C42: =IF(ISNUMBER(B42),IF(B42>=0.8,"Alto: en línea o por encima del benchmark habitual de 80% en hotelería.",IF(B42>=0.6,"Aceptable, aunque por debajo del benchmark habitual de 80%.","Bajo: conviene priorizar acciones correctivas.")) & " Resultado actual: " & TEXT(B42,"0%"),"Cargar los datos de la encuesta para calcular el CSAT.") -> Aceptable, aunque por debajo del benchmark habitual de 80%. Resultado actual: 70%

Sheet Customer Journey Map
A1: Customer Journey Map (As Is) — Familia Huésped de Hotel Costa Azul
A2: Estado actual del recorrido, con detalle por subetapa | Hotel Costa Azul (caso ficticio) | familias en temporada alta
A4: Etapa | B4: 1. Descubrimiento y reserva | D4: 2. Llegada y check-in | F4: 3. Estadía | H4: 4. Check-out y salida | J4: 5. Postestadía y fidelización
A5: Subetapa | B5: a) Búsqueda y comparación (Booking, Google) | C5: b) Reserva y consultas previas | D5: a) Llegada y check-in | E5: b) Primeras impresiones / acompañamiento | F5: a) Habitación (limpieza, mantenimiento) | G5: b) Servicios del hotel (desayuno, pileta/playa) | H5: a) Check-out | I5: b) Salida / despedida | J5: a) Interacción post-estadía (reseñas) | K5: b) Fidelización / recompra
A6: Descripción de la etapa | B6: Momento en que el huésped potencial descubre el hotel y realiza la reserva, comparando opciones y consultando disponibilidad. | D6: El huésped llega al hotel, realiza el check-in y recibe las primeras impresiones del lugar y del trato del personal. | F6: El huésped se aloja en la habitación y utiliza los servicios del hotel (desayuno, pileta, playa) durante su estadía. | H6: El huésped realiza el check-out y se retira del hotel. | J6: Después de la estadía, el huésped interactúa con la marca en redes, deja reseñas y decide si vuelve en temporadas futuras.
A7: Touchpoints | B7: Booking.com, Google Maps, recomendaciones de otras familias | C7: WhatsApp, Instagram, mensajería de Booking.com | D7: Recepción, mostrador de check-in | E7: Personal de recepción/conserjería, pasillos, habitación | F7: Habitación (aire acondicionado, wifi, limpieza) | G7: Comedor/desayuno, pileta, personal de atención | H7: Recepción, mostrador de check-out | I7: Personal de recepción, dueños del hotel | J7: Google Maps, Booking.com, Instagram | K7: Rutina de vacaciones anuales, recomendación boca a boca
A8: Acciones del huésped | B8: Compara precios, fotos y reseñas de distintos hoteles antes de decidir | C8: Consulta disponibilidad, tarifas y servicios (cochera, desayuno) antes de reservar | D8: Llega con la familia y el equipaje, espera para hacer el check-in | E8: Es acompañada a la habitación y recibe información básica del hotel | F8: Se instala y usa la habitación durante la estadía | G8: Desayuna, usa la pileta o va a la playa, interactúa con el personal | H8: Realiza el check-out y paga el saldo si corresponde | I8: Se despide; a veces recibe un trato personalizado de los dueños | J8: Deja una reseña o comenta en redes sobre su experiencia | K8: Vuelve la temporada siguiente y recomienda el hotel a otras familias
A9: Pensamientos y emociones | B9: Expectativa mezclada con cautela; busca señales de confianza (reseñas, fotos reales) | C9: Necesita confirmar detalles antes de comprometerse con la reserva | D9: Ansiedad por "ya estar" en la habitación, sobre todo con chicos cansados del viaje | E9: Forma la primera impresión general del hotel en estos minutos | F9: Confort y tranquilidad si todo funciona bien; frustración si hay fallas | G9: Valora la calidez del trato, aunque compare mentalmente el desayuno con el precio pagado | H9: Evalúa mentalmente si la estadía valió el precio pagado | I9: Sensación de cierre cálido si los dueños se acercan a despedirse | J9: Ganas de compartir una buena experiencia, o de señalar lo que no funcionó | K9: Sensación de pertenencia: "es como visitar a la familia, no un hotel más"
A10: Puntos de dolor | B10: El precio de temporada alta puede generar dudas antes incluso de reservar | C10: Demoras de días en responder consultas por WhatsApp/Instagram | D10: Check-in demorado por poco personal en recepción en temporada alta | E10: Habitación no lista a la hora comprometida, sin aviso previo | F10: Problemas de mantenimiento (aire acondicionado, wifi) sin resolución rápida | G10: Desayuno percibido como básico en relación al precio de temporada alta | H10: Mismo riesgo de demora que en el check-in si hay varios check-outs simultáneos | I10: Inconsistencia si el trato personalizado depende de qué dueño/empleado está de turno | J10: Sin protocolo de respuesta a reseñas, se pierde la oportunidad de mostrar mejora ante comentarios negativos | K10: Esa lealtad depende mucho del vínculo con los dueños actuales; un cambio de gestión podría debilitarla
A11: Oportunidades | B11: Responder públicamente a reseñas sobre precio-valor, explicando qué incluye la tarifa | C11: Definir un tiempo de respuesta máximo para consultas de reserva | D11: Reforzar la dotación de recepción en los horarios de mayor llegada de temporada alta | E11: Avisar proactivamente si la habitación va a demorar, y ofrecer una alternativa (guardar equipaje, área de espera) | F11: Checklist de mantenimiento preventivo entre estadías + protocolo de resolución rápida de reclamos técnicos | G11: Revisar la propuesta de desayuno o comunicar claramente qué incluye la tarifa | H11: Ofrecer check-out anticipado/exprés para quienes salen temprano | I11: Sistematizar un gesto de despedida (los dueños se acercan siempre a saludar antes de la salida) | J11: Responder todas las reseñas (positivas y negativas) con un mensaje personalizado de los dueños | K11: Documentar y transmitir la cultura de trato cálido al personal nuevo, para que no dependa de una sola persona
A12: Evidencia / Fuente | B12: Reseñas sobre precio caro para lo que ofrece (Hallazgo 5) | C12: Consulta sobre cochera sin respuesta por 2 días; comentarios de Instagram sin respuesta (Hallazgo 4) | D12: Reseña sobre check-in demorado con varios huéspedes llegando juntos (Hallazgo 2) | E12: Reseña sobre habitación no lista hasta las 15h sin aviso (Hallazgo 2) | F12: Reseñas sobre aire acondicionado y wifi (Hallazgo 3) | G12: Reseña sobre desayuno básico para el precio de temporada alta (Hallazgo 5) | H12: Perfil de temporada alta con salidas concentradas en la mañana | I12: Reseñas que destacan el trato de los dueños como diferencial (Hallazgo 1) | J12: Reseñas variadas en Google Maps/Booking (Hallazgos 2, 3 y 5) | K12: Cita "es como visitar a la familia" (Hallazgo 1)

Sheet Customer Journey Map (To Be)
A1: Customer Journey Map (To Be) — Familia Huésped de Hotel Costa Azul
A2: Estado deseado del recorrido, con detalle por subetapa | Hotel Costa Azul (caso ficticio) | familias en temporada alta
A4: Etapa | B4: 1. Descubrimiento y reserva | D4: 2. Llegada y check-in | F4: 3. Estadía | H4: 4. Check-out y salida | J4: 5. Postestadía y fidelización
A5: Subetapa | B5: a) Búsqueda y comparación (Booking, Google) | C5: b) Reserva y consultas previas | D5: a) Llegada y check-in | E5: b) Primeras impresiones / acompañamiento | F5: a) Habitación (limpieza, mantenimiento) | G5: b) Servicios del hotel (desayuno, pileta/playa) | H5: a) Check-out | I5: b) Salida / despedida | J5: a) Interacción post-estadía (reseñas) | K5: b) Fidelización / recompra
A6: Descripción de la etapa | B6: El huésped potencial encuentra información clara sobre precios y servicios, y recibe respuestas rápidas a sus consultas antes de reservar. | D6: La llegada y el check-in se resuelven con rapidez, incluso en temporada alta, con comunicación proactiva si hay demoras. | F6: La estadía se disfruta sin sobresaltos: habitación en buen estado y servicios que se corresponden con lo prometido. | H6: El check-out es rápido y el huésped se retira con una despedida cálida y consistente. | J6: El vínculo con el hotel se sostiene más allá de los dueños actuales, gracias a una cultura de trato cálido transmitida a todo el personal.
A7: Touchpoints (mejorados) | B7: Perfil de Booking/Google con fotos actualizadas y respuestas públicas a reseñas de precio | C7: WhatsApp Business con tiempo de respuesta definido | D7: Recepción con personal reforzado en horarios de mayor llegada | E7: Recepción con aviso proactivo si la habitación se demora | F7: Habitación con mantenimiento preventivo entre estadías | G7: Comedor con propuesta de desayuno revisada y comunicada | H7: Check-out anticipado/exprés para salidas tempranas | I7: Recepción con protocolo de despedida de los dueños | J7: Respuesta personalizada a cada reseña (Google/Booking) | K7: Cultura de trato cálido transmitida a todo el personal, comunicación de novedades
A8: Acciones del huésped | B8: Encuentra información clara sobre qué incluye la tarifa antes de reservar | C8: Recibe respuesta a sus consultas (cochera, servicios) en pocas horas | D8: Hace el check-in rápido, incluso con varias familias llegando juntas | E8: Es avisada con anticipación si hay demora y recibe una alternativa mientras espera | F8: Usa la habitación sin sobresaltos técnicos (aire acondicionado, wifi funcionando) | G8: Desayuna sintiendo que el servicio se corresponde con la tarifa pagada | H8: Hace un check-out rápido, sin esperas innecesarias | I8: Se va con una despedida cálida y consistente, con o sin los dueños presentes | J8: Recibe una respuesta genuina a su reseña, sea positiva o negativa | K8: Vuelve la temporada siguiente y recomienda el hotel, más allá de quién lo atienda
A9: Pensamientos y emociones (esperados) | B9: Confianza en que el precio se corresponde con el servicio | C9: Tranquilidad para reservar con confianza | D9: Alivio de "ya estar" sin esperar de más con los chicos cansados | E9: Sensación de ser tenida en cuenta, aunque haya un imprevisto | F9: Confort y tranquilidad durante toda la estadía | G9: Percepción de valor sostenida durante la estadía | H9: Cierre práctico y sin fricciones antes de viajar de vuelta | I9: Sensación de cierre cálido, sostenida más allá de quién esté en el turno | J9: Sensación de ser escuchado, incluso cuando algo salió mal | K9: Lealtad al hotel como marca/familia, no solo a los dueños actuales
A10: Mejora implementada | B10: Respuesta pública a reseñas sobre precio-valor, explicando qué incluye la tarifa | C10: SLA de respuesta a consultas de reserva (WhatsApp/Instagram) de 24 horas o menos | D10: Refuerzo de personal de recepción en los horarios pico de check-in de temporada alta | E10: Protocolo de aviso proactivo + alternativa (guardar equipaje, área de espera) ante demoras | F10: Checklist de mantenimiento preventivo entre estadías + protocolo de resolución rápida de reclamos técnicos | G10: Revisión de la propuesta de desayuno y comunicación clara de qué incluye la tarifa | H10: Opción de check-out anticipado/exprés para quienes salen temprano | I10: Sistematizar un gesto de despedida (mensaje o saludo) que no dependa de que los dueños estén presentes | J10: Protocolo de respuesta a todas las reseñas, con mensaje personalizado de los dueños | K10: Documentar y capacitar al personal nuevo en la cultura de trato cálido del hotel
A11: Resultado esperado / KPI | B11: % de reseñas de precio respondidas públicamente | C11: Tiempo de respuesta promedio a consultas de reserva | D11: Tiempo promedio de check-in en temporada alta | E11: % de habitaciones listas a la hora comprometida | F11: Tiempo de resolución de reclamos de mantenimiento (objetivo: mismo día) | G11: % de huéspedes que perciben el desayuno como "acorde al precio" (encuesta) | H11: Tiempo promedio de check-out en temporada alta | I11: Consistencia del trato percibida en la despedida (encuesta) | J11: % de reseñas respondidas dentro de las 48 horas | K11: % de huéspedes recurrentes que repiten temporada · NPS histórico
A12: Vinculación con hallazgo (As Is) | B12: Refuerza el Hallazgo 5 (percepción de precio-valor) | C12: Resuelve el Hallazgo 4 (consultas y reservas digitales) | D12: Resuelve el Hallazgo 2 (demoras en check-in) | E12: Resuelve el Hallazgo 2 (demoras en check-in) | F12: Resuelve el Hallazgo 3 (fallas de mantenimiento) | G12: Resuelve el Hallazgo 5 (percepción de precio-valor) | H12: Complementa la mejora del Hallazgo 2 (demoras en check-in) | I12: Refuerza el Hallazgo 1 (calidez y trato del personal) | J12: Complementa los Hallazgos 2, 3 y 5 | K12: Refuerza el Hallazgo 1 y da sostenibilidad a largo plazo

Sheet Service Blueprint
A1: Service Blueprint — Familia Huésped de Hotel Costa Azul
A2: Complementa el Customer Journey Map con la vista interna del servicio: frontstage, backstage y procesos de soporte | Hotel Costa Azul (caso ficticio)
A4: Etapa | B4: 1. Descubrimiento y reserva | D4: 2. Llegada y check-in | F4: 3. Estadía | H4: 4. Check-out y salida | J4: 5. Postestadía y fidelización
A5: Subetapa | B5: a) Búsqueda y comparación (Booking, Google) | C5: b) Reserva y consultas previas | D5: a) Llegada y check-in | E5: b) Primeras impresiones / acompañamiento | F5: a) Habitación (limpieza, mantenimiento) | G5: b) Servicios del hotel (desayuno, pileta/playa) | H5: a) Check-out | I5: b) Salida / despedida | J5: a) Interacción post-estadía (reseñas) | K5: b) Fidelización / recompra
A6: Evidencia física | B6: Perfil de Booking.com/Google Maps, fotos, reseñas | C6: Mensajes de WhatsApp/Instagram, confirmación de reserva | D6: Mostrador de recepción, formulario de check-in | E6: Pasillos, habitación, cartel de bienvenida | F6: Habitación, aire acondicionado, wifi, mobiliario | G6: Comedor, buffet de desayuno, pileta | H6: Mostrador de check-out, factura/ticket | I6: Puerta de salida, saludo de los dueños | J6: Reseña en Google Maps/Booking, publicación en Instagram | K6: Comunicación de novedades, contacto de temporada siguiente
A7: Acciones del huésped | B7: Compara precios, fotos y reseñas de distintos hoteles antes de decidir | C7: Consulta disponibilidad, tarifas y servicios (cochera, desayuno) antes de reservar | D7: Llega con la familia y el equipaje, espera para hacer el check-in | E7: Es acompañada a la habitación y recibe información básica del hotel | F7: Se instala y usa la habitación durante la estadía | G7: Desayuna, usa la pileta o va a la playa, interactúa con el personal | H7: Realiza el check-out y paga el saldo si corresponde | I7: Se despide; a veces recibe un trato personalizado de los dueños | J7: Deja una reseña o comenta en redes sobre su experiencia | K7: Vuelve la temporada siguiente y recomienda el hotel a otras familias
A8: ▬▬▬ LÍNEA DE INTERACCIÓN ▬▬▬
A9: Frontstage (personal de contacto directo) | B9: Sin interacción humana directa en este momento | C9: Dueño/recepción responde consultas de disponibilidad y servicios | D9: Recepcionista/dueño realiza el check-in | E9: Personal acompaña al huésped a la habitación | F9: Mantenimiento atiende reclamos técnicos si el huésped los reporta | G9: Personal de comedor/pileta atiende al huésped | H9: Recepcionista/dueño realiza el check-out y cobra el saldo | I9: Dueños o personal se despiden del huésped | J9: Dueños responden las reseñas y comentarios | K9: Dueños/personal recuerdan a huéspedes recurrentes y los contactan para la temporada siguiente
A10: ▬▬▬ LÍNEA DE VISIBILIDAD ▬▬▬
A11: Backstage (personal sin contacto directo) | B11: Actualización de fotos/tarifas en Booking/Google; respuesta a reseñas de precio | C11: Gestión del calendario de disponibilidad y tarifas | D11: Verificación de disponibilidad y asignación de habitaciones | E11: Coordinación con mucamas sobre el estado de las habitaciones | F11: Mantenimiento preventivo entre estadías, gestión de reclamos técnicos | G11: Compras y preparación del desayuno, mantenimiento de la pileta | H11: Conciliación de cuenta, actualización de disponibilidad de la habitación | I11: Sin actividad backstage relevante en este momento | J11: Gestión de reputación online, seguimiento de reclamos pendientes | K11: Gestión de una base de huéspedes recurrentes, capacitación de personal nuevo en la cultura del hotel
A12: ▬▬▬ LÍNEA DE INTERACCIÓN INTERNA ▬▬▬
A13: Procesos de soporte (sistemas y proveedores) | B13: Booking.com, Google Business Profile | C13: WhatsApp Business, sistema de reservas/calendario | D13: Sistema de gestión hotelera (PMS), planilla de check-in/check-out | E13: Planilla de estado de habitaciones (limpia/lista/en preparación) | F13: Checklist de mantenimiento, proveedor de servicio técnico | G13: Proveedores de insumos de desayuno, servicio de mantenimiento de pileta | H13: Sistema de gestión hotelera (PMS) | I13: — | J13: Google Business Profile, Booking.com Extranet | K13: Base de datos de huéspedes (CRM básico), material de capacitación interno
A14: Punto de fallo potencial (riesgo) | B14: Reseñas de precio sin respuesta erosionan la confianza antes de reservar (Hallazgo 5) | C14: Demoras de días en responder consultas de reserva (Hallazgo 4) | D14: Check-in demorado por poco personal en temporada alta (Hallazgo 2) | E14: Habitación no lista a la hora comprometida, sin aviso previo (Hallazgo 2) | F14: Fallas de mantenimiento sin resolución rápida (Hallazgo 3) | G14: Desayuno percibido como básico para el precio de temporada alta (Hallazgo 5) | H14: Demoras si hay varios check-outs simultáneos en temporada alta | I14: El trato personalizado depende de qué dueño/empleado está de turno (Hallazgo 1) | J14: Sin protocolo de respuesta, se pierde la oportunidad de mostrar mejora ante reseñas negativas | K14: La lealtad depende mucho del vínculo con los dueños actuales; un cambio de gestión podría debilitarla (Hallazgo 1)
A16: Referencias: por encima de la línea de interacción, lo que el huésped hace y ve (front stage). Entre la línea de visibilidad y la de interacción interna, lo que hace el personal sin contacto directo (back stage). Debajo, los sistemas y proveedores que sostienen el servicio.

Sheet Insights y Oportunidades
A1: Síntesis de Hallazgos, Insights y Priorización
A2: Hotel Costa Azul (caso ficticio) — misma metodología aplicada a Clínica Bermejo y Café Aurora
A4: # | B4: Hallazgo | C4: Insight | D4: Etapa del CJM más afectada | E4: Impacto (Alto/Medio/Bajo) | F4: Prioridad sugerida
A5: 1 | B5: La calidez y personalización del trato de los dueños genera fidelidad fuerte y visitas recurrentes año tras año. | C5: El vínculo emocional con los dueños es el principal diferencial frente a hoteles de cadena, pero depende de personas puntuales. | D5: Salida / despedida | E5: Alto | F5: Media
A6: 2 | B6: En temporada alta, el check-in y la disponibilidad de la habitación generan demoras y frustración. | C6: La capacidad operativa no siempre acompaña los picos de demanda estacional, afectando la primera impresión. | D6: Llegada y check-in | E6: Alto | F6: Alta
A7: 3 | B7: Existen fallas de mantenimiento (aire acondicionado, wifi) sin resolución rápida durante la estadía. | C7: La falta de mantenimiento preventivo entre estadías genera fricciones evitables que afectan la percepción de calidad. | D7: Estadía | E7: Alto | F7: Alta
A8: 4 | B8: Las consultas de reserva por WhatsApp/Instagram no siempre reciben respuesta rápida. | C8: La demora en la respuesta digital puede hacer perder reservas frente a opciones más ágiles. | D8: Descubrimiento y reserva | E8: Medio | F8: Media
A9: 5 | B9: Parte de los huéspedes percibe que el precio de temporada alta no se corresponde con la calidad/servicios ofrecidos (ej. desayuno). | C9: La percepción de precio-valor es sensible en temporada alta y puede afectar la recomendación y el retorno. | D9: Estadía | E9: Alto | F9: Alta
